tradssat-0.1.10.dist-info/METADATA
tradssat-0.1.10.dist-info/WHEEL
tradssat-0.1.10.dist-info/licenses/LICENSE
tradssat/__init__.py
tradssat/exper/__init__.py
tradssat/exper/exper_file.py
tradssat/exper/exper_vars.py
tradssat/genotype/__init__.py
tradssat/genotype/gen_file.py
tradssat/genotype/vars_/__init__.py
tradssat/genotype/vars_/_cropgro.py
tradssat/genotype/vars_/_cropsim.py
tradssat/genotype/vars_/_utils.py
tradssat/genotype/vars_/alfrm.py
tradssat/genotype/vars_/bacer.py
tradssat/genotype/vars_/bacrp.py
tradssat/genotype/vars_/bhgro.py
tradssat/genotype/vars_/bmfrm.py
tradssat/genotype/vars_/bmgro.py
tradssat/genotype/vars_/bngro.py
tradssat/genotype/vars_/brfrm.py
tradssat/genotype/vars_/brgro.py
tradssat/genotype/vars_/bscer.py
tradssat/genotype/vars_/cbgro.py
tradssat/genotype/vars_/chgro.py
tradssat/genotype/vars_/cngro.py
tradssat/genotype/vars_/cogro.py
tradssat/genotype/vars_/cpgro.py
tradssat/genotype/vars_/cscas.py
tradssat/genotype/vars_/csyca.py
tradssat/genotype/vars_/fbgro.py
tradssat/genotype/vars_/g0gro.py
tradssat/genotype/vars_/gbgro.py
tradssat/genotype/vars_/mlcer.py
tradssat/genotype/vars_/mzcer.py
tradssat/genotype/vars_/mzixm.py
tradssat/genotype/vars_/pialo.py
tradssat/genotype/vars_/pngro.py
tradssat/genotype/vars_/ppgro.py
tradssat/genotype/vars_/prgro.py
tradssat/genotype/vars_/ptsub.py
tradssat/genotype/vars_/ricer.py
tradssat/genotype/vars_/riorz.py
tradssat/genotype/vars_/sbgro.py
tradssat/genotype/vars_/sccan.py
tradssat/genotype/vars_/sccsp.py
tradssat/genotype/vars_/sfgro.py
tradssat/genotype/vars_/sgcer.py
tradssat/genotype/vars_/sugro.py
tradssat/genotype/vars_/swcer.py
tradssat/genotype/vars_/tmgro.py
tradssat/genotype/vars_/tnaro.py
tradssat/genotype/vars_/traro.py
tradssat/genotype/vars_/vbgro.py
tradssat/genotype/vars_/whaps.py
tradssat/genotype/vars_/whcer.py
tradssat/genotype/vars_/whcrp.py
tradssat/mgrs/__init__.py
tradssat/mgrs/exp_mgr.py
tradssat/mgrs/gen_mgr.py
tradssat/mgrs/input.py
tradssat/mgrs/mgr.py
tradssat/mgrs/out.py
tradssat/mgrs/soil_mgr.py
tradssat/mgrs/wth_mgr.py
tradssat/out/__init__.py
tradssat/out/et.py
tradssat-0.1.10.dist-info/RECORD
