Metadata-Version: 2.1
Name: tradssat
Version: 0.1.10
Summary: DSSAT input and output file reader and writer
Author-Email: Julien Malard-Adam <julien.malard@mail.mcgill.ca>, श्रेया संजय यादव <shreya.yadav@mail.mcgill.ca>
License: MIT
Classifier: Programming Language :: Python :: 3 :: Only
Classifier: License :: OSI Approved :: MIT License
Requires-Python: <4.0,>=3.10
Requires-Dist: numpy>=1.26.2
Requires-Dist: pandas>=2.1.4
Requires-Dist: chardet>=5.2.0
